{
  "1":{
    "sentence":"머리, 날개는 독수리의 형상을, 몸통, 뒷발은 사자의 형상을 하고 있는 상상의 동물은?",
    "score":2,
    "choices":[
      "그리핀",
      "스핑크스",
      "페라리",
      "페가소스",
      "살라만더"
    ],
    "answer":1
  },

  "2":{
    "sentence":"음력으로 매월 마지막 날에 뜨는 달의 이름은?",
    "score":3,
    "choices":[
      "초승달",
      "반달",
      "해품달",
      "그믐달",
      "막달"
    ],
    "answer":4
  },

  "3":{
    "sentence":"우유를 유산균으로 발효시키면 이것이 된다고 한다. 이것은?",
    "score":2,
    "choices":[
      "카나페",
      "크림",
      "요구르트",
      "버터",
      "분유"
    ],
    "answer":3
  },

  "4":{
    "sentence":"타인에게 귀여움 받기 위해 어린아이의 말투나 태도로 애교 또는 응석을 부리는 일을 뜻하는 것은?",
    "score":1,
    "choices":[
      "눈갱",
      "저주",
      "꿍꼬또",
      "귀갱",
      "어리광"
    ],
    "answer":5
  },

  "5":{
    "sentence":"모나리자를 그린 화가의 이름은?",
    "score":2,
    "choices":[
      "레오나르도 디카프리오",
      "모차르트",
      "모나미자",
      "레오나르도 다빈치",
      "정우창"
    ],
    "answer":4
  }
}
